example/README.md
example/test_example.py
example/src/servicer.py
example/src/test.proto
example/src/stub/.keepdir
pytest_grpc_aio/__init__.py
pytest_grpc_aio/plugin.py
pytest_grpc_aio-0.2.0.dist-info/licenses/LICENSE
pytest_grpc_aio-0.2.0.dist-info/METADATA
pytest_grpc_aio-0.2.0.dist-info/WHEEL
pytest_grpc_aio-0.2.0.dist-info/entry_points.txt
pytest_grpc_aio-0.2.0.dist-info/top_level.txt
pytest_grpc_aio-0.2.0.dist-info/RECORD
